wolf_comm/__init__.py
wolf_comm/constants.py
wolf_comm/create_session.py
wolf_comm/helpers.py
wolf_comm/models.py
wolf_comm/py.typed
wolf_comm/token_auth.py
wolf_comm/wolf_client.py
wolf_comm-0.0.47.dist-info/licenses/LICENSE.txt
wolf_comm-0.0.47.dist-info/METADATA
wolf_comm-0.0.47.dist-info/WHEEL
wolf_comm-0.0.47.dist-info/top_level.txt
wolf_comm-0.0.47.dist-info/RECORD
