Metadata-Version: 2.4
Name: wolf_comm
Version: 0.0.47
Summary: A package to communicate with Wolf SmartSet Cloud
Home-page: https://github.com/janrothkegel/wolf-comm
Author: Jan Rothkegel
Author-email: jan.rothkegel@web.de
Classifier: Programming Language :: Python :: 3
Classifier: Operating System :: OS Independent
Classifier: License :: OSI Approved :: Apache Software License
License-File: LICENSE.txt
Requires-Dist: aiohttp
Requires-Dist: httpx
Requires-Dist: lxml
Requires-Dist: pkce
Requires-Dist: shortuuid
Dynamic: author
Dynamic: author-email
Dynamic: classifier
Dynamic: description
Dynamic: description-content-type
Dynamic: home-page
Dynamic: license-file
Dynamic: requires-dist
Dynamic: summary
